mgexpose/__init__.py
mgexpose/__main__.py
mgexpose/clustering_parser.py
mgexpose/eggnog.py
mgexpose/gene.py
mgexpose/gene_annotator.py
mgexpose/gene_calling.py
mgexpose/gffio.py
mgexpose/handle_args.py
mgexpose/island_processing.py
mgexpose/islands.py
mgexpose/phage.py
mgexpose/recombinase_scan.py
mgexpose/recombinases.py
mgexpose/readers/__init__.py
mgexpose/readers/readers.py
mgexpose/utils/__init__.py
mgexpose/utils/chunk_reader.py
mgexpose/writers/__init__.py
mgexpose-3.8.0.dist-info/licenses/LICENSE
mgexpose-3.8.0.dist-info/METADATA
mgexpose-3.8.0.dist-info/WHEEL
mgexpose-3.8.0.dist-info/entry_points.txt
mgexpose-3.8.0.dist-info/top_level.txt
mgexpose-3.8.0.dist-info/RECORD
