Metadata-Version: 2.4
Name: mgexpose
Version: 3.8.0
Home-page: https://github.com/cschu/mgexpose
Author: Christian Schudoma, Anastasia Grekova, Supriya Khedkar
Author-email: christian.schudoma@embl.de, anastasiia.grekova@embl.de, khedkar@bioquant.uni-heidelberg.de 
License: MIT
Keywords: microbial genome mobile genetic element detection
Classifier: Development Status :: 4 - Beta
Classifier: Topic :: Scientific/Engineering :: Bio-Informatics
Classifier: License :: OSI Approved :: MIT License
Classifier: Operating System :: POSIX :: Linux
Classifier: Programming Language :: Python :: 3.7
Classifier: Programming Language :: Python :: 3.8
Classifier: Programming Language :: Python :: 3.9
Classifier: Programming Language :: Python :: 3.10
Classifier: Programming Language :: Python :: 3.11
Classifier: Programming Language :: Python :: 3.12
Classifier: Programming Language :: Python :: 3.13
License-File: LICENSE
Requires-Dist: pyhmmer
Requires-Dist: pyrodigal
Dynamic: author
Dynamic: author-email
Dynamic: classifier
Dynamic: home-page
Dynamic: keywords
Dynamic: license
Dynamic: license-file
Dynamic: requires-dist
